fastapi_events/__init__.py
fastapi_events/constants.py
fastapi_events/dispatcher.py
fastapi_events/errors.py
fastapi_events/middleware.py
fastapi_events/py.typed
fastapi_events/typing.py
fastapi_events/utils.py
fastapi_events/handlers/__init__.py
fastapi_events/handlers/aws.py
fastapi_events/handlers/base.py
fastapi_events/handlers/echo.py
fastapi_events/handlers/gcp.py
fastapi_events/handlers/local.py
fastapi_events/handlers/null.py
fastapi_events/otel/__init__.py
fastapi_events/otel/attributes.py
fastapi_events/otel/utils.py
fastapi_events/otel/propagate/__init__.py
fastapi_events/otel/propagate/dummy.py
fastapi_events/otel/trace/__init__.py
fastapi_events/otel/trace/dummy.py
fastapi_events/registry/__init__.py
fastapi_events/registry/base.py
fastapi_events/registry/payload_schema.py
tests/__init__.py
tests/test_dispatcher.py
tests/test_event_payload_schema_registry.py
fastapi_events-0.12.2.dist-info/LICENSE
fastapi_events-0.12.2.dist-info/METADATA
fastapi_events-0.12.2.dist-info/WHEEL
fastapi_events-0.12.2.dist-info/top_level.txt
fastapi_events-0.12.2.dist-info/RECORD
