Metadata-Version: 2.1
Name: fastapi-events
Version: 0.12.2
Summary: Event dispatching library for FastAPI
Home-page: https://github.com/melvinkcx/fastapi-events
Author: Melvin Koh
Author-email: melvinkcx@gmail.com
Keywords: starlette,fastapi,starlite,pydantic
Classifier: Programming Language :: Python :: 3.10
Classifier: Intended Audience :: Developers
Classifier: Programming Language :: Python :: 3.9
Classifier: Development Status :: 5 - Production/Stable
Classifier: Operating System :: OS Independent
Classifier: Programming Language :: Python :: 3.13
Classifier: Programming Language :: Python :: 3.11
Classifier: Environment :: Web Environment
Classifier: Programming Language :: Python
Classifier: License :: OSI Approved :: MIT License
Classifier: Programming Language :: Python :: 3.12
Classifier: Programming Language :: Python :: 3.8
Classifier: Programming Language :: Python :: 3
Requires-Python: >=3.7
License-File: LICENSE
Provides-Extra: aws
Requires-Dist: boto3>=1.14; extra == "aws"
Provides-Extra: google
Requires-Dist: google-cloud-pubsub>=2.13.6; extra == "google"
Provides-Extra: otel
Requires-Dist: opentelemetry-api<2.0,>=1.12.0; extra == "otel"
